.DS_Store
glycompare/__init__.py
glycompare/clustering_analysis.py
glycompare/extract_substructures.py
glycompare/glycan_io.py
glycompare/hierarchical_enrichment.py
glycompare/json_utility.py
glycompare/merge_substructure_vec.py
glycompare/nglycan_alignment.py
glycompare/parse_markov.py
glycompare/pipeline_functions.py
glycompare/plot_glycan_utilities.py
glycompare/process_glycoprofiles.py
glycompare/select_motifs.py
glycompare/test_glycan_io.py
glycompare-1.0.3.dist-info/LICENSE
glycompare-1.0.3.dist-info/METADATA
glycompare-1.0.3.dist-info/WHEEL
glycompare-1.0.3.dist-info/top_level.txt
glycompare-1.0.3.dist-info/RECORD
