Metadata-Version: 2.1
Name: glycompare
Version: 1.0.3
Summary: GlyCompare
Home-page: https://github.com/LewisLabUCSD/GlyCompare
Author: B.B., B.P.K
Author-email: bobao@eng.ucsd.edu
License: UNKNOWN
Platform: UNKNOWN
Classifier: Programming Language :: Python :: 3
Classifier: License :: OSI Approved :: MIT License
Classifier: Operating System :: OS Independent
Requires-Dist: glypy (==0.12.4)
Requires-Dist: Cython
Requires-Dist: pandas
Requires-Dist: numpy
Requires-Dist: seaborn
Requires-Dist: networkx (==1.11)
Requires-Dist: ndex
Requires-Dist: rdflib
Requires-Dist: xlrd (==1.2)
Requires-Dist: beautifulsoup4
Requires-Dist: SPARQLWrapper
